certbot_dns_mijn_host/__init__.py
certbot_dns_mijn_host/mijn_host.py
certbot_dns_mijn_host/test_mijn_host.py
certbot_dns_mijn_host-0.0.8.dist-info/LICENSE
certbot_dns_mijn_host-0.0.8.dist-info/METADATA
certbot_dns_mijn_host-0.0.8.dist-info/WHEEL
certbot_dns_mijn_host-0.0.8.dist-info/entry_points.txt
certbot_dns_mijn_host-0.0.8.dist-info/top_level.txt
certbot_dns_mijn_host-0.0.8.dist-info/RECORD
