Metadata-Version: 2.1
Name: certbot-dns-mijn-host
Version: 0.0.8
Summary: Certbot DNS plugin for mijn.host service, enabling the automation of DNS-01 challenges for issuing wildcard SSL certificates. This plugin simplifies the process of obtaining and renewing SSL certificates by integrating directly with the DNS API of mijn.host Service, making it ideal for system administrators and DevOps professionals managing secure web services.
Home-page: https://pypi.org/project/certbot-dns-mijn-host/
Classifier: Development Status :: 5 - Production/Stable
Classifier: Environment :: Plugins
Classifier: Intended Audience :: System Administrators
Classifier: License :: OSI Approved :: Apache Software License
Classifier: Operating System :: POSIX :: Linux
Classifier: Programming Language :: Python
Classifier: Programming Language :: Python :: 3
Classifier: Topic :: Internet :: Name Service (DNS)
Classifier: Topic :: Security
Classifier: Topic :: Security :: Cryptography
Classifier: Topic :: System :: Networking
Classifier: Topic :: System :: Systems Administration
Classifier: Topic :: Utilities
Requires-Python: >=2.7
License-File: LICENSE
Requires-Dist: acme>=2.11.0
Requires-Dist: certbot>=2.11.0
Requires-Dist: certifi==2024.8.30
Requires-Dist: cffi==1.17.0
Requires-Dist: charset-normalizer==3.3.2
Requires-Dist: ConfigArgParse==1.7
Requires-Dist: configobj==5.0.8
Requires-Dist: cryptography>=3.2.1
Requires-Dist: distro==1.9.0
Requires-Dist: idna==3.8
Requires-Dist: josepy==1.14.0
Requires-Dist: parsedatetime==2.6
Requires-Dist: pycparser==2.22
Requires-Dist: PyOpenSSL>=25.0.0
Requires-Dist: pyRFC3339==1.1
Requires-Dist: pytz==2024.1
Requires-Dist: requests==2.32.3
Requires-Dist: ruff==0.6.3
Requires-Dist: setuptools==74.0.0
Requires-Dist: six==1.16.0
Requires-Dist: urllib3==2.2.2
Requires-Dist: wheel==0.44.0
